[
  {
    "title": "The Garfield Movie",
    "id": 16641,
    "alt_title": "Grettir bíómyndin",
    "release_year": 2024,
    "poster_url": "https://kvikmyndir.is/images/poster/outlook-grettir-po-1709984574.jpg",
    "rating_urls": [
      "http://imdb.com/title/tt5779228",
      "http://imdb.com/title/tt5779228"
    ],
    "content_rating": "Öllum leyfð",
    "description": "Kötturinn Grettir er á leið í stórskemmtilegt útivistar-ævintýri en eftir óvænta endurfundi með löngu týndum föður sínum, neyðast Grettir og hundurinn Oddi til að yfirgefa dekurlíf sitt og ganga til liðs við pabbann í hættulegri ránsferð.",
    "genres": [
      "Gaman",
      "Ævintýri",
      "Teiknað"
    ],
    "duration_in_mins": 101,
    "language": [
      "Enska"
    ],
    "trailer_url": "https://www.youtube.com/watch?v=IeFWNtMo1Fs",
    "cinema_showtimes": {
      "Smárabíó": [
        {
          "time": "2024-06-01T10:20:00.000Z",
          "purchase_url": "https://kvikmyndir.is/kvikmyndir/showtime_redirect.php?id=0febdfc1-996c-4953-a59b-96aa4b900d60",
          "hall": "MAX"
        },
        {
          "time": "2024-06-01T10:30:00.000Z",
          "purchase_url": "https://kvikmyndir.is/kvikmyndir/showtime_redirect.php?id=9f7fcbfa-7e6c-4d2b-915b-6ca2f8c99e80",
          "hall": "Salur 4"
        },
        {
          "time": "2024-06-01T12:40:00.000Z",
          "purchase_url": "https://kvikmyndir.is/kvikmyndir/showtime_redirect.php?id=72e5f683-98c6-4a65-9bdc-a818adf8d23c",
          "hall": "MAX"
        },
        {
          "time": "2024-06-01T12:50:00.000Z",
          "purchase_url": "https://kvikmyndir.is/kvikmyndir/showtime_redirect.php?id=899cbf8f-26e1-4130-9fc6-28ffd4cf3fa4",
          "hall": "Salur 4"
        },
        {
          "time": "2024-06-01T15:00:00.000Z",
          "purchase_url": "https://kvikmyndir.is/kvikmyndir/showtime_redirect.php?id=92e7a9ca-6391-4ba9-8d59-384041364cb5",
          "hall": "MAX"
        },
        {
          "time": "2024-06-01T17:20:00.000Z",
          "purchase_url": "https://kvikmyndir.is/kvikmyndir/showtime_redirect.php?id=e506e346-622c-4097-8231-7e693ea03efd",
          "hall": "MAX"
        },
        {
          "time": "2024-06-01T17:30:00.000Z",
          "purchase_url": "https://kvikmyndir.is/kvikmyndir/showtime_redirect.php?id=20d65b6f-a35f-4e8b-8ec1-5788a8caaa8d",
          "hall": "Salur 4"
        }
      ],
      "Sambíóin Kringlunni": [
        {
          "time": "2024-06-01T12:00:00.000Z",
          "purchase_url": "https://kvikmyndir.is/kvikmyndir/showtime_redirect.php?id=ce933ba5-bc0e-4f41-88a7-62d6f08c647c",
          "hall": "Salur 3"
        },
        {
          "time": "2024-06-01T14:15:00.000Z",
          "purchase_url": "https://kvikmyndir.is/kvikmyndir/showtime_redirect.php?id=888d3739-42ca-41e6-8703-7f4ee7f44ce1",
          "hall": "Salur 3"
        },
        {
          "time": "2024-06-01T16:30:00.000Z",
          "purchase_url": "https://kvikmyndir.is/kvikmyndir/showtime_redirect.php?id=3ef8cda1-5a1b-46f2-bbda-46ce1d45ea72",
          "hall": "Salur 3"
        },
        {
          "time": "2024-06-01T18:10:00.000Z",
          "purchase_url": "https://kvikmyndir.is/kvikmyndir/showtime_redirect.php?id=d1c04822-260b-450c-9620-7bf968609f67",
          "hall": "Salur 2"
        }
      ],
      "Sambíóin Akureyri": [
        {
          "time": "2024-06-01T12:00:00.000Z",
          "purchase_url": "https://kvikmyndir.is/kvikmyndir/showtime_redirect.php?id=3c693f9f-4c97-4823-a26b-1bb1e2a72736",
          "hall": "Salur 1"
        },
        {
          "time": "2024-06-01T14:20:00.000Z",
          "purchase_url": "https://kvikmyndir.is/kvikmyndir/showtime_redirect.php?id=50439e64-875e-42ad-8533-2f111b41d014",
          "hall": "Salur 1"
        },
        {
          "time": "2024-06-01T17:00:00.000Z",
          "purchase_url": "https://kvikmyndir.is/kvikmyndir/showtime_redirect.php?id=1b37a271-3fe0-470f-b3aa-8ad8969e8980",
          "hall": "Salur 2"
        }
      ],
      "Sambíóin Egilshöll": [
        {
          "time": "2024-06-01T13:00:00.000Z",
          "purchase_url": "https://kvikmyndir.is/kvikmyndir/showtime_redirect.php?id=f2e6024f-48ad-4d54-834e-34b5ee57cfb8",
          "hall": "Salur 1"
        },
        {
          "time": "2024-06-01T15:10:00.000Z",
          "purchase_url": "https://kvikmyndir.is/kvikmyndir/showtime_redirect.php?id=613b1dea-baf1-438b-ba16-0d78fb422e1e",
          "hall": "Salur 1"
        },
        {
          "time": "2024-06-01T17:20:00.000Z",
          "purchase_url": "https://kvikmyndir.is/kvikmyndir/showtime_redirect.php?id=fc67c780-4ce9-46cc-86c9-d5a855f960ef",
          "hall": "Salur 1"
        },
        {
          "time": "2024-06-01T20:00:00.000Z",
          "purchase_url": "https://kvikmyndir.is/kvikmyndir/showtime_redirect.php?id=4650118e-4a0e-4548-a613-e703155bc44c",
          "hall": "Salur 3"
        }
      ],
      "Sambíóin Álfabakka": [
        {
          "time": "2024-06-01T13:00:00.000Z",
          "purchase_url": "https://kvikmyndir.is/kvikmyndir/showtime_redirect.php?id=dd13f327-032e-484b-b31e-b5dca26113ae",
          "hall": "Salur 1"
        },
        {
          "time": "2024-06-01T13:00:00.000Z",
          "purchase_url": "https://kvikmyndir.is/kvikmyndir/showtime_redirect.php?id=bf964407-2a70-4c5a-8aec-52fc4dc9cf71",
          "hall": "Salur B"
        },
        {
          "time": "2024-06-01T15:10:00.000Z",
          "purchase_url": "https://kvikmyndir.is/kvikmyndir/showtime_redirect.php?id=4ca92cb2-429d-4dc8-bcb8-cac9cd354675",
          "hall": "Salur B"
        },
        {
          "time": "2024-06-01T15:20:00.000Z",
          "purchase_url": "https://kvikmyndir.is/kvikmyndir/showtime_redirect.php?id=14a1e898-b9fb-4f91-8fef-cfbbbdc597e8",
          "hall": "Salur 1"
        },
        {
          "time": "2024-06-01T17:20:00.000Z",
          "purchase_url": "https://kvikmyndir.is/kvikmyndir/showtime_redirect.php?id=bc6b2d96-2c91-4f2d-8a0f-4b4fbaf5e4ff",
          "hall": "Salur B"
        },
        {
          "time": "2024-06-01T17:40:00.000Z",
          "purchase_url": "https://kvikmyndir.is/kvikmyndir/showtime_redirect.php?id=a96470fb-9c33-4559-8248-2f0f49eb6f49",
          "hall": "Salur 1"
        },
        {
          "time": "2024-06-01T19:30:00.000Z",
          "purchase_url": "https://kvikmyndir.is/kvikmyndir/showtime_redirect.php?id=4fe127ce-bec4-4171-b920-fb624e91354e",
          "hall": "Salur B"
        }
      ],
      "Laugarásbíó": [
        {
          "time": "2024-06-01T13:30:00.000Z",
          "purchase_url": "https://kvikmyndir.is/kvikmyndir/showtime_redirect.php?id=8476d8f0-e6a5-42e2-920a-c012793ba8fc",
          "hall": "Salur A"
        },
        {
          "time": "2024-06-01T15:45:00.000Z",
          "purchase_url": "https://kvikmyndir.is/kvikmyndir/showtime_redirect.php?id=063af87f-3a7c-4f25-846f-6d8871aaa210",
          "hall": "AXL"
        }
      ],
      "Sambíóin Keflavík": [
        {
          "time": "2024-06-01T15:00:00.000Z",
          "purchase_url": "https://kvikmyndir.is/kvikmyndir/showtime_redirect.php?id=4703522d-cc7a-4e64-9c61-578d93a38d33",
          "hall": "Salur 1"
        },
        {
          "time": "2024-06-01T17:20:00.000Z",
          "purchase_url": "https://kvikmyndir.is/kvikmyndir/showtime_redirect.php?id=61cee2c5-5b0c-4f4d-b59e-0ca884846c9f",
          "hall": "Salur 2"
        }
      ]
    }
  },
  {
    "title": "Snerting",
    "id": 16860,
    "alt_title": "Touch",
    "release_year": 2024,
    "poster_url": "https://kvikmyndir.is/images/poster/1713557969523_ho00001787-1713776856.jpg",
    "rating_urls": [
      "http://imdb.com/title/tt23468836",
      "http://imdb.com/title/tt23468836"
    ],
    "content_rating": "Bönnuð innan 9 ára",
    "description": "Kristófer, sjötugur ekkill, kominn á eftirlaun, leggur upp í ferð án fyrirheits, þegar heims-faraldurinn er skollinn á, í von um að finna skýringu á því hvað orðið hafi um kærustu hans sem hvarf sporlaust frá London 50 árum áður. För hans leiðir hann yfir hálfan hnöttinn og alla leið til Japans.",
    "genres": [
      "Rómantík",
      "Drama"
    ],
    "duration_in_mins": 120,
    "language": [
      "Enska"
    ],
    "trailer_url": "https://www.youtube.com/watch?v=y5fXuZ3ns_c",
    "cinema_showtimes": {
      "Smárabíó": [
        {
          "time": "2024-06-01T11:20:00.000Z",
          "purchase_url": "https://kvikmyndir.is/kvikmyndir/showtime_redirect.php?id=1f6b198b-3f84-4bcc-b1e2-c7d072901ba0",
          "hall": "LÚXUS"
        },
        {
          "time": "2024-06-01T14:00:00.000Z",
          "purchase_url": "https://kvikmyndir.is/kvikmyndir/showtime_redirect.php?id=84bbe779-21d7-4c7a-b1c4-530088b5f718",
          "hall": "LÚXUS"
        },
        {
          "time": "2024-06-01T14:40:00.000Z",
          "purchase_url": "https://kvikmyndir.is/kvikmyndir/showtime_redirect.php?id=7336ed55-cfbe-47d5-9acc-72f169eac3fc",
          "hall": "Salur 2"
        },
        {
          "time": "2024-06-01T16:40:00.000Z",
          "purchase_url": "https://kvikmyndir.is/kvikmyndir/showtime_redirect.php?id=1c690dee-0df7-4e79-99df-8d24a42c70e4",
          "hall": "LÚXUS"
        },
        {
          "time": "2024-06-01T17:20:00.000Z",
          "purchase_url": "https://kvikmyndir.is/kvikmyndir/showtime_redirect.php?id=0e3bbcfd-46f0-4c42-8339-9a0cfb7a00a6",
          "hall": "Salur 2"
        },
        {
          "time": "2024-06-01T19:20:00.000Z",
          "purchase_url": "https://kvikmyndir.is/kvikmyndir/showtime_redirect.php?id=e8108d45-c5c6-40cf-915b-31404ae43dba",
          "hall": "LÚXUS"
        },
        {
          "time": "2024-06-01T19:40:00.000Z",
          "purchase_url": "https://kvikmyndir.is/kvikmyndir/showtime_redirect.php?id=65c6322d-096a-448a-bffa-2ff1d815e4e1",
          "hall": "MAX"
        },
        {
          "time": "2024-06-01T22:00:00.000Z",
          "purchase_url": "https://kvikmyndir.is/kvikmyndir/showtime_redirect.php?id=0b8881fd-3564-4631-95d2-50415679c1e6",
          "hall": "LÚXUS"
        },
        {
          "time": "2024-06-01T22:10:00.000Z",
          "purchase_url": "https://kvikmyndir.is/kvikmyndir/showtime_redirect.php?id=88701f6c-8201-47be-ac6b-8b8af7d0d68e",
          "hall": "Salur 4"
        }
      ],
      "Sambíóin Kringlunni": [
        {
          "time": "2024-06-01T13:30:00.000Z",
          "purchase_url": "https://kvikmyndir.is/kvikmyndir/showtime_redirect.php?id=890760c8-5152-4d63-b138-b12408205b85",
          "hall": "Salur 1"
        },
        {
          "time": "2024-06-01T13:50:00.000Z",
          "purchase_url": "https://kvikmyndir.is/kvikmyndir/showtime_redirect.php?id=7d7e36b8-16d4-4d57-a854-3e4689804372",
          "hall": "Ásberg"
        },
        {
          "time": "2024-06-01T16:00:00.000Z",
          "purchase_url": "https://kvikmyndir.is/kvikmyndir/showtime_redirect.php?id=8efe32ec-7de4-4ea2-9ed0-45c86c710407",
          "hall": "Salur 1"
        },
        {
          "time": "2024-06-01T16:20:00.000Z",
          "purchase_url": "https://kvikmyndir.is/kvikmyndir/showtime_redirect.php?id=63dbce09-bea8-4162-b612-45013e590e3a",
          "hall": "Ásberg"
        },
        {
          "time": "2024-06-01T18:30:00.000Z",
          "purchase_url": "https://kvikmyndir.is/kvikmyndir/showtime_redirect.php?id=4e5da5f1-3243-41d5-9432-2c4c2ef689f6",
          "hall": "Salur 1"
        },
        {
          "time": "2024-06-01T19:00:00.000Z",
          "purchase_url": "https://kvikmyndir.is/kvikmyndir/showtime_redirect.php?id=6ffe9fd7-056b-402d-9ff0-67923bacf13b",
          "hall": "Ásberg"
        },
        {
          "time": "2024-06-01T20:20:00.000Z",
          "purchase_url": "https://kvikmyndir.is/kvikmyndir/showtime_redirect.php?id=e81255a8-2c2e-44ac-b9e9-1ee2d4abc00f",
          "hall": "Salur 2"
        },
        {
          "time": "2024-06-01T21:00:00.000Z",
          "purchase_url": "https://kvikmyndir.is/kvikmyndir/showtime_redirect.php?id=7b1c9b38-f991-47d5-ab90-55652c68a134",
          "hall": "Salur 1"
        },
        {
          "time": "2024-06-01T21:40:00.000Z",
          "purchase_url": "https://kvikmyndir.is/kvikmyndir/showtime_redirect.php?id=9f7f534e-cb2e-41d5-83f5-6394141e4813",
          "hall": "Ásberg"
        }
      ],
      "Laugarásbíó": [
        {
          "time": "2024-06-01T13:30:00.000Z",
          "purchase_url": "https://kvikmyndir.is/kvikmyndir/showtime_redirect.php?id=be2d3740-aaac-460d-bbc6-42df8b7309bb",
          "hall": "Salur B"
        },
        {
          "time": "2024-06-01T16:00:00.000Z",
          "purchase_url": "https://kvikmyndir.is/kvikmyndir/showtime_redirect.php?id=4995d8f6-7535-4684-aae2-c185db44ef37",
          "hall": "Salur A"
        },
        {
          "time": "2024-06-01T18:00:00.000Z",
          "purchase_url": "https://kvikmyndir.is/kvikmyndir/showtime_redirect.php?id=0d511ba3-0321-4226-9d81-eaf305338549",
          "hall": "AXL"
        },
        {
          "time": "2024-06-01T20:30:00.000Z",
          "purchase_url": "https://kvikmyndir.is/kvikmyndir/showtime_redirect.php?id=3df861c3-e1a5-4fc6-b722-59b26e195976",
          "hall": "AXL"
        }
      ],
      "Sambíóin Akureyri": [
        {
          "time": "2024-06-01T14:20:00.000Z",
          "purchase_url": "https://kvikmyndir.is/kvikmyndir/showtime_redirect.php?id=dd0d663b-fc81-4c11-9433-e53d00c695b8",
          "hall": "Salur 2"
        },
        {
          "time": "2024-06-01T16:40:00.000Z",
          "purchase_url": "https://kvikmyndir.is/kvikmyndir/showtime_redirect.php?id=9217b721-3d11-4813-b890-eb317a18aa76",
          "hall": "Salur 1"
        },
        {
          "time": "2024-06-01T19:20:00.000Z",
          "purchase_url": "https://kvikmyndir.is/kvikmyndir/showtime_redirect.php?id=4a28fef0-9154-4ff3-a38b-7ba81b1f32e4",
          "hall": "Salur 1"
        }
      ],
      "Bíó Paradís": [
        {
          "time": "2024-06-01T16:40:00.000Z",
          "purchase_url": "https://kvikmyndir.is/kvikmyndir/showtime_redirect.php?id=616b6734-53c6-4100-b2e6-3c06a2081019",
          "hall": "Salur 1"
        },
        {
          "time": "2024-06-01T19:00:00.000Z",
          "purchase_url": "https://kvikmyndir.is/kvikmyndir/showtime_redirect.php?id=9834b7bd-eae4-425a-bef9-dcd12acf7a34",
          "hall": "Salur 1"
        },
        {
          "time": "2024-06-01T21:20:00.000Z",
          "purchase_url": "https://kvikmyndir.is/kvikmyndir/showtime_redirect.php?id=f6746a67-c554-40a4-9662-ef9663ce7977",
          "hall": "Salur 1"
        }
      ],
      "Sambíóin Keflavík": [
        {
          "time": "2024-06-01T17:40:00.000Z",
          "purchase_url": "https://kvikmyndir.is/kvikmyndir/showtime_redirect.php?id=1a7d5dd9-fd6b-4731-8cf0-52bd4440315e",
          "hall": "Salur 1"
        },
        {
          "time": "2024-06-01T20:20:00.000Z",
          "purchase_url": "https://kvikmyndir.is/kvikmyndir/showtime_redirect.php?id=382657bf-1fb5-4f9b-9cce-37d1b1f14a17",
          "hall": "Salur 1"
        }
      ]
    }
  },
  {
    "title": "Furiosa: A Mad Max Saga",
    "id": 16607,
    "alt_title": "Furiosa fór á toppinn",
    "release_year": 2024,
    "poster_url": "https://kvikmyndir.is/images/poster/1763431_500-1713977804.jpg",
    "rating_urls": [
      "http://imdb.com/title/tt12037194",
      "http://imdb.com/title/tt12037194"
    ],
    "content_rating": "Bönnuð innan 16 ára",
    "description": "Heimurinn er á heljarþröm og hinni ungu Furiosu er rænt úr Green Place of Many Mothers og færð mótorhjólagenginu sem stríðsherrann Dementus fer fyrir. Á ferð sinni yfir einskismannslandið koma þau að borgvirki sem Immortan Joe stýrir.  Hann og Dementus berjast um yfirráðin og Furiosa þarf að lifa af margar raunir á sama tíma og hún leitar að leið heim.",
    "genres": [
      "Spenna",
      "Vísindaskáldskapur",
      "Ævintýri"
    ],
    "duration_in_mins": 149,
    "language": [
      "Enska"
    ],
    "trailer_url": "https://www.youtube.com/watch?v=XJMuhwVlca4",
    "cinema_showtimes": {
      "Sambíóin Álfabakka": [
        {
          "time": "2024-06-01T13:00:00.000Z",
          "purchase_url": "https://kvikmyndir.is/kvikmyndir/showtime_redirect.php?id=8efc9774-6774-4791-9494-a3c72d30cfdb",
          "hall": "Lúxus VIP"
        },
        {
          "time": "2024-06-01T13:30:00.000Z",
          "purchase_url": "https://kvikmyndir.is/kvikmyndir/showtime_redirect.php?id=d5613af2-f1f5-4de8-aa31-ee7d2a128d09",
          "hall": "Salur 3"
        },
        {
          "time": "2024-06-01T16:00:00.000Z",
          "purchase_url": "https://kvikmyndir.is/kvikmyndir/showtime_redirect.php?id=473d4c5e-b06b-4192-8f9d-4cf6e51a5735",
          "hall": "Lúxus VIP"
        },
        {
          "time": "2024-06-01T17:20:00.000Z",
          "purchase_url": "https://kvikmyndir.is/kvikmyndir/showtime_redirect.php?id=5a5a8122-0974-4490-bd7f-daae24c6f26a",
          "hall": "Salur A"
        },
        {
          "time": "2024-06-01T19:00:00.000Z",
          "purchase_url": "https://kvikmyndir.is/kvikmyndir/showtime_redirect.php?id=7ffdc3ec-3bcb-4cf0-8b45-846b7472a995",
          "hall": "Lúxus VIP"
        },
        {
          "time": "2024-06-01T20:00:00.000Z",
          "purchase_url": "https://kvikmyndir.is/kvikmyndir/showtime_redirect.php?id=36c1966b-0139-479b-b152-7026c80aeeb7",
          "hall": "Salur 1"
        },
        {
          "time": "2024-06-01T22:00:00.000Z",
          "purchase_url": "https://kvikmyndir.is/kvikmyndir/showtime_redirect.php?id=c194815f-5de9-479d-bce5-ac90f83b131d",
          "hall": "Lúxus VIP"
        }
      ],
      "Sambíóin Egilshöll": [
        {
          "time": "2024-06-01T14:00:00.000Z",
          "purchase_url": "https://kvikmyndir.is/kvikmyndir/showtime_redirect.php?id=5a9f36f3-59d2-4c91-9afd-460386ed5392",
          "hall": "Salur 2"
        },
        {
          "time": "2024-06-01T17:00:00.000Z",
          "purchase_url": "https://kvikmyndir.is/kvikmyndir/showtime_redirect.php?id=28117d61-d193-468e-b4ae-795aca81819d",
          "hall": "Salur 2"
        },
        {
          "time": "2024-06-01T19:30:00.000Z",
          "purchase_url": "https://kvikmyndir.is/kvikmyndir/showtime_redirect.php?id=92753c12-69e3-4248-a496-f399d1174e9f",
          "hall": "Salur 1"
        },
        {
          "time": "2024-06-01T22:00:00.000Z",
          "purchase_url": "https://kvikmyndir.is/kvikmyndir/showtime_redirect.php?id=85f1834a-6d2c-4c34-8fe9-3b37fad0b8a6",
          "hall": "Salur 2"
        }
      ],
      "Laugarásbíó": [
        {
          "time": "2024-06-01T18:30:00.000Z",
          "purchase_url": "https://kvikmyndir.is/kvikmyndir/showtime_redirect.php?id=f874bc1e-846c-41da-b81f-de8dc74ecfd5",
          "hall": "Salur A"
        },
        {
          "time": "2024-06-01T21:30:00.000Z",
          "purchase_url": "https://kvikmyndir.is/kvikmyndir/showtime_redirect.php?id=3d2026ad-c8b6-4912-a8bb-c91338904df1",
          "hall": "Salur A"
        }
      ],
      "Sambíóin Kringlunni": [
        {
          "time": "2024-06-01T18:50:00.000Z",
          "purchase_url": "https://kvikmyndir.is/kvikmyndir/showtime_redirect.php?id=2e197818-4cee-40eb-9721-40c3b96b7890",
          "hall": "Salur 3"
        },
        {
          "time": "2024-06-01T21:50:00.000Z",
          "purchase_url": "https://kvikmyndir.is/kvikmyndir/showtime_redirect.php?id=6484cdf4-7148-41f6-be76-00c439eec961",
          "hall": "Salur 3"
        }
      ],
      "Sambíóin Akureyri": [
        {
          "time": "2024-06-01T19:20:00.000Z",
          "purchase_url": "https://kvikmyndir.is/kvikmyndir/showtime_redirect.php?id=a5da7426-83ad-4c04-adf5-e1b90b04751c",
          "hall": "Salur 2"
        },
        {
          "time": "2024-06-01T22:00:00.000Z",
          "purchase_url": "https://kvikmyndir.is/kvikmyndir/showtime_redirect.php?id=24954e8a-71fb-4800-b2d5-afec4e3a0ae6",
          "hall": "Salur 1"
        }
      ],
      "Sambíóin Keflavík": [
        {
          "time": "2024-06-01T20:00:00.000Z",
          "purchase_url": "https://kvikmyndir.is/kvikmyndir/showtime_redirect.php?id=30d07f6e-e5ef-4845-ab6a-b26b334142c2",
          "hall": "Salur 2"
        }
      ],
      "Smárabíó": [
        {
          "time": "2024-06-01T20:00:00.000Z",
          "purchase_url": "https://kvikmyndir.is/kvikmyndir/showtime_redirect.php?id=310cd61c-ecf6-4319-b795-3e7a843a62db",
          "hall": "Salur 2"
        },
        {
          "time": "2024-06-01T22:15:00.000Z",
          "purchase_url": "https://kvikmyndir.is/kvikmyndir/showtime_redirect.php?id=67a527f4-0d7d-44de-9519-4dea70a826b2",
          "hall": "MAX"
        }
      ]
    }
  },
  {
    "title": "If",
    "id": 16640,
    "alt_title": "Imaginary Friend",
    "release_year": 2024,
    "poster_url": "https://kvikmyndir.is/images/poster/16640_500.jpg",
    "rating_urls": [
      "http://imdb.com/title/tt11152168",
      "http://imdb.com/title/tt11152168"
    ],
    "content_rating": "Öllum leyfð",
    "description": "Saga af stúlku sem kemst að því að hún getur séð alla ímyndaða vini. Hún heldur af stað í ævintýralegt ferðalag til tengja krakka aftur við gleymdu ímynduðu vini sína.",
    "genres": [
      "Gaman",
      "Drama",
      "Fjölskylda"
    ],
    "duration_in_mins": 104,
    "language": [
      "Enska"
    ],
    "trailer_url": "https://www.youtube.com/watch?v=el0N_MDcp0Y",
    "cinema_showtimes": {
      "Smárabíó": [
        {
          "time": "2024-06-01T10:40:00.000Z",
          "purchase_url": "https://kvikmyndir.is/kvikmyndir/showtime_redirect.php?id=9101ac3b-50d0-4e68-aabd-5dc9f01d4633",
          "hall": "Salur 5"
        },
        {
          "time": "2024-06-01T13:10:00.000Z",
          "purchase_url": "https://kvikmyndir.is/kvikmyndir/showtime_redirect.php?id=b6cbd6e3-5a62-4a03-b142-c8c6e814e461",
          "hall": "Salur 5"
        },
        {
          "time": "2024-06-01T15:10:00.000Z",
          "purchase_url": "https://kvikmyndir.is/kvikmyndir/showtime_redirect.php?id=6a4485bb-38f3-42ab-8594-7ef3af305e3c",
          "hall": "Salur 4"
        }
      ],
      "Sambíóin Kringlunni": [
        {
          "time": "2024-06-01T11:40:00.000Z",
          "purchase_url": "https://kvikmyndir.is/kvikmyndir/showtime_redirect.php?id=c2c7fe7f-968a-47e7-ad1f-c0287358e02d",
          "hall": "Salur 2"
        },
        {
          "time": "2024-06-01T13:50:00.000Z",
          "purchase_url": "https://kvikmyndir.is/kvikmyndir/showtime_redirect.php?id=82c0e849-1de7-4337-b858-06cb36e1e8ce",
          "hall": "Salur 2"
        },
        {
          "time": "2024-06-01T16:00:00.000Z",
          "purchase_url": "https://kvikmyndir.is/kvikmyndir/showtime_redirect.php?id=374bd0c6-4e9f-42b7-8317-9a15491160c7",
          "hall": "Salur 2"
        }
      ],
      "Sambíóin Akureyri": [
        {
          "time": "2024-06-01T12:00:00.000Z",
          "purchase_url": "https://kvikmyndir.is/kvikmyndir/showtime_redirect.php?id=5a82ae4c-715f-4980-ad12-9deff94a225d",
          "hall": "Salur 2"
        }
      ],
      "Sambíóin Egilshöll": [
        {
          "time": "2024-06-01T13:00:00.000Z",
          "purchase_url": "https://kvikmyndir.is/kvikmyndir/showtime_redirect.php?id=00be30ea-13fa-4620-9989-66a2d754bdca",
          "hall": "Salur 3"
        },
        {
          "time": "2024-06-01T15:20:00.000Z",
          "purchase_url": "https://kvikmyndir.is/kvikmyndir/showtime_redirect.php?id=afe67c10-95ac-4eb0-9111-db0e16fa3437",
          "hall": "Salur 3"
        },
        {
          "time": "2024-06-01T17:40:00.000Z",
          "purchase_url": "https://kvikmyndir.is/kvikmyndir/showtime_redirect.php?id=ceaebbbe-f7b2-4c88-9efe-920396027408",
          "hall": "Salur 3"
        }
      ],
      "Sambíóin Álfabakka": [
        {
          "time": "2024-06-01T13:00:00.000Z",
          "purchase_url": "https://kvikmyndir.is/kvikmyndir/showtime_redirect.php?id=e544ba88-b892-4855-9f3c-84b8cc90b987",
          "hall": "Salur A"
        },
        {
          "time": "2024-06-01T15:10:00.000Z",
          "purchase_url": "https://kvikmyndir.is/kvikmyndir/showtime_redirect.php?id=72275faf-91b6-43d1-bee5-ea6d0b6ceb4e",
          "hall": "Salur A"
        },
        {
          "time": "2024-06-01T17:00:00.000Z",
          "purchase_url": "https://kvikmyndir.is/kvikmyndir/showtime_redirect.php?id=c6a61cbd-fe2a-4ffd-83fa-09380053b041",
          "hall": "Salur 2"
        },
        {
          "time": "2024-06-01T19:10:00.000Z",
          "purchase_url": "https://kvikmyndir.is/kvikmyndir/showtime_redirect.php?id=81b4c329-7fad-42b2-bcb0-0936dfdb3b34",
          "hall": "Salur 2"
        }
      ],
      "Sambíóin Keflavík": [
        {
          "time": "2024-06-01T15:00:00.000Z",
          "purchase_url": "https://kvikmyndir.is/kvikmyndir/showtime_redirect.php?id=d491ccf2-b4e2-4897-97e9-c9def9aa3f7e",
          "hall": "Salur 2"
        }
      ],
      "Laugarásbíó": [
        {
          "time": "2024-06-01T16:00:00.000Z",
          "purchase_url": "https://kvikmyndir.is/kvikmyndir/showtime_redirect.php?id=0610e83d-6ec9-4980-98a9-75161e65fadf",
          "hall": "Salur B"
        }
      ]
    }
  },
  {
    "title": "Kingdom of the Planet of the Apes",
    "id": 16554,
    "alt_title": "Furiosa fór á toppinn",
    "release_year": 2024,
    "poster_url": "https://kvikmyndir.is/images/poster/1765005_500-1713976472.jpg",
    "rating_urls": [
      "http://imdb.com/title/tt11389872",
      "http://imdb.com/title/tt11389872"
    ],
    "content_rating": "Bönnuð innan 12 ára",
    "description": "Mörgum árum eftir valdatíð Caesars eru apar ráðandi dýrategund á Jörðinnni og búa í sátt og samlyndi við menn sem hafa dregið sig í hlé. Á sama tíma og nýr herskár api byggir upp veldi sitt, heldur ungur api af stað í erfitt ferðalag sem lætur hann efast um allt sem hann vissi um fortíðina og ýtir á hann að taka ákvarðanir sem skilgreina munu framtíð bæði apa og manna.",
    "genres": [
      "Spenna",
      "Vísindaskáldskapur"
    ],
    "duration_in_mins": 145,
    "language": [
      "Enska"
    ],
    "trailer_url": "https://www.youtube.com/watch?v=XtFI7SNtVpY",
    "cinema_showtimes": {
      "Sambíóin Egilshöll": [
        {
          "time": "2024-06-01T13:00:00.000Z",
          "purchase_url": "https://kvikmyndir.is/kvikmyndir/showtime_redirect.php?id=31f77127-852c-45fa-b4c0-f46f1a1f08ef",
          "hall": "Salur 4"
        },
        {
          "time": "2024-06-01T16:00:00.000Z",
          "purchase_url": "https://kvikmyndir.is/kvikmyndir/showtime_redirect.php?id=0e8429ec-5a5f-4529-a5f5-1a6f049f7d75",
          "hall": "Salur 4"
        },
        {
          "time": "2024-06-01T19:20:00.000Z",
          "purchase_url": "https://kvikmyndir.is/kvikmyndir/showtime_redirect.php?id=e6d7eaad-dfe5-4b05-b96a-d1901e454cd3",
          "hall": "Salur 4"
        },
        {
          "time": "2024-06-01T22:10:00.000Z",
          "purchase_url": "https://kvikmyndir.is/kvikmyndir/showtime_redirect.php?id=65583f27-f594-485f-b545-3339e0bc52a1",
          "hall": "Salur 3"
        }
      ],
      "Sambíóin Álfabakka": [
        {
          "time": "2024-06-01T16:30:00.000Z",
          "purchase_url": "https://kvikmyndir.is/kvikmyndir/showtime_redirect.php?id=fc1232ef-0a93-461c-bcc5-56592809e502",
          "hall": "Salur 3"
        },
        {
          "time": "2024-06-01T20:20:00.000Z",
          "purchase_url": "https://kvikmyndir.is/kvikmyndir/showtime_redirect.php?id=f6ab927c-a27a-4e2e-8b13-0c42501ce6bf",
          "hall": "Salur A"
        }
      ],
      "Smárabíó": [
        {
          "time": "2024-06-01T19:00:00.000Z",
          "purchase_url": "https://kvikmyndir.is/kvikmyndir/showtime_redirect.php?id=ec2eae17-05ed-4dd9-abda-af0af0f09216",
          "hall": "Salur 5"
        }
      ]
    }
  },
  {
    "title": "The Fall Guy",
    "id": 16572,
    "alt_title": "Ímyndaðir vinir á toppnum",
    "release_year": 2024,
    "poster_url": "https://kvikmyndir.is/images/poster/1750525_500-1710066762.jpg",
    "rating_urls": [
      "http://imdb.com/title/tt1684562",
      "http://imdb.com/title/tt1684562"
    ],
    "content_rating": "Bönnuð innan 12 ára",
    "description": "Áhættuleikarinn Colt Seavers, sem nýlega lenti í slysi sem hefði getað bundið enda á ferilinn, þarf að elta uppi týnda kvikmyndastjörnu, leysa úr samsæri og reyna að ná aftur í draumadísina á sama tíma og hann verður að mæta í vinnuna dag hvern. Gæti eitthvað af þessu mögulega heppnast?",
    "genres": [
      "Spenna",
      "Gaman",
      "Drama"
    ],
    "duration_in_mins": 126,
    "language": [
      "Enska"
    ],
    "trailer_url": "https://www.youtube.com/watch?v=j7jPnwVGdZ8",
    "cinema_showtimes": {
      "Laugarásbíó": [
        {
          "time": "2024-06-01T18:10:00.000Z",
          "purchase_url": "https://kvikmyndir.is/kvikmyndir/showtime_redirect.php?id=85d47923-e435-4bd1-866f-ab0124169e14",
          "hall": "Salur B"
        },
        {
          "time": "2024-06-01T21:00:00.000Z",
          "purchase_url": "https://kvikmyndir.is/kvikmyndir/showtime_redirect.php?id=c025e8ec-059f-4dbb-922a-241ebe81de71",
          "hall": "Salur B"
        }
      ],
      "Sambíóin Álfabakka": [
        {
          "time": "2024-06-01T19:30:00.000Z",
          "purchase_url": "https://kvikmyndir.is/kvikmyndir/showtime_redirect.php?id=8009b324-9d9e-4fc1-8e40-81b713c9b0d4",
          "hall": "Salur 3"
        }
      ],
      "Smárabíó": [
        {
          "time": "2024-06-01T22:10:00.000Z",
          "purchase_url": "https://kvikmyndir.is/kvikmyndir/showtime_redirect.php?id=7495d7a8-4a8b-4ab2-890a-0a8acd284ccc",
          "hall": "Salur 5"
        }
      ]
    }
  },
  {
    "title": "The Strangers: Chapter 1",
    "id": 16877,
    "alt_title": "Dregin yfir mulið gler og glóandi kol",
    "release_year": 2024,
    "poster_url": "https://kvikmyndir.is/images/poster/16877_500.jpg",
    "rating_urls": [
      "http://imdb.com/title/tt22050754",
      "http://imdb.com/title/tt22050754"
    ],
    "content_rating": "Bönnuð innan 16 ára",
    "description": "Eftir að bíll þeirra bilar í uggvekjandi litlum bæ neyðist ungt par til að gista í kofa fyrir utan bæinn. Þau verða skelfingu lostin þegar þrír grímuklæddir menn ógna þeim alla nóttina af miklu miskunnarleysi og án nokkurrar ástæðu.",
    "genres": [
      "Hrollvekja"
    ],
    "duration_in_mins": 91,
    "language": [
      "Enska"
    ],
    "trailer_url": "https://www.youtube.com/watch?v=DSudLoJy2ok",
    "cinema_showtimes": {
      "Sambíóin Egilshöll": [
        {
          "time": "2024-06-01T20:00:00.000Z",
          "purchase_url": "https://kvikmyndir.is/kvikmyndir/showtime_redirect.php?id=75724e1e-da05-4f93-94c2-0ef44a6f5d10",
          "hall": "Salur 2"
        },
        {
          "time": "2024-06-01T22:30:00.000Z",
          "purchase_url": "https://kvikmyndir.is/kvikmyndir/showtime_redirect.php?id=ddec8ba6-e641-41d6-ac4c-9a685c02418e",
          "hall": "Salur 1"
        }
      ],
      "Sambíóin Álfabakka": [
        {
          "time": "2024-06-01T21:40:00.000Z",
          "purchase_url": "https://kvikmyndir.is/kvikmyndir/showtime_redirect.php?id=11b01a95-ca03-48b4-a18c-6dc832dadde6",
          "hall": "Salur B"
        }
      ],
      "Sambíóin Akureyri": [
        {
          "time": "2024-06-01T22:20:00.000Z",
          "purchase_url": "https://kvikmyndir.is/kvikmyndir/showtime_redirect.php?id=88bc18f9-2320-483f-9afc-e1cfeb839325",
          "hall": "Salur 2"
        }
      ]
    }
  },
  {
    "title": "Tarot",
    "id": 16728,
    "alt_title": "Horrorscope",
    "release_year": 2024,
    "poster_url": "https://kvikmyndir.is/images/poster/16728_500.jpg",
    "rating_urls": [
      "http://imdb.com/title/tt14088510",
      "http://imdb.com/title/tt14088510"
    ],
    "content_rating": "Bönnuð innan 16 ára",
    "description": "Þegar vinahópur brýtur helga reglu Tarotspila þá óafvitandi leysa þau úr læðingi yfirgengilega illsku sem var föst í hinum  fordæmdu spilum. Eitt af öðrum þurfa þau nú að horfast í augu við örlög sín og lenda í baráttu upp á líf og dauða.",
    "genres": [
      "Hrollvekja"
    ],
    "duration_in_mins": 92,
    "language": [
      "Enska"
    ],
    "trailer_url": "https://www.youtube.com/watch?v=XNTEjJm4WXg",
    "cinema_showtimes": {
      "Smárabíó": [
        {
          "time": "2024-06-01T19:50:00.000Z",
          "purchase_url": "https://kvikmyndir.is/kvikmyndir/showtime_redirect.php?id=7f6c4d5a-a0f9-4f21-a13c-9b47aa417f50",
          "hall": "Salur 4"
        }
      ],
      "Sambíóin Álfabakka": [
        {
          "time": "2024-06-01T22:10:00.000Z",
          "purchase_url": "https://kvikmyndir.is/kvikmyndir/showtime_redirect.php?id=d5047483-678c-4e94-9f8c-79b76fc71cc4",
          "hall": "Salur 3"
        }
      ],
      "Sambíóin Egilshöll": [
        {
          "time": "2024-06-01T22:20:00.000Z",
          "purchase_url": "https://kvikmyndir.is/kvikmyndir/showtime_redirect.php?id=6221878c-e10c-423c-ac60-7aba0042391c",
          "hall": "Salur 4"
        }
      ]
    }
  },
  {
    "title": "10 líf",
    "id": 16787,
    "alt_title": "10 Lives",
    "release_year": 2024,
    "poster_url": "https://kvikmyndir.is/images/poster/10lif-vefposter-1709986913.jpg",
    "rating_urls": [
      "http://imdb.com/title/tt7959138",
      "http://imdb.com/title/tt7959138"
    ],
    "content_rating": "Öllum leyfð",
    "description": "Beggi er ofdekraður köttur tekur sem sjálfsögðum hlut þeirri lukku sem hann varð fyrir þegar honum var bjargað af Rósu. Þegar hann missir níunda líf sitt grípa örlögin inní og senda hann í ævintýri lífs síns.",
    "genres": [
      "Gaman",
      "Ævintýri",
      "Teiknað"
    ],
    "duration_in_mins": 88,
    "language": [
      "Enska"
    ],
    "trailer_url": "https://www.youtube.com/watch?v=mQ2jRkRJW-c",
    "cinema_showtimes": {
      "Smárabíó": [
        {
          "time": "2024-06-01T10:20:00.000Z",
          "purchase_url": "https://kvikmyndir.is/kvikmyndir/showtime_redirect.php?id=1ac12135-3065-4073-b01b-9bdf150ae312",
          "hall": "Salur 2"
        },
        {
          "time": "2024-06-01T12:30:00.000Z",
          "purchase_url": "https://kvikmyndir.is/kvikmyndir/showtime_redirect.php?id=6fd809ec-834d-4c8f-b771-8678700cddc2",
          "hall": "Salur 2"
        },
        {
          "time": "2024-06-01T15:40:00.000Z",
          "purchase_url": "https://kvikmyndir.is/kvikmyndir/showtime_redirect.php?id=aec31a63-0163-4c57-b1e4-3d46d25438e8",
          "hall": "Salur 5"
        }
      ]
    }
  },
  {
    "title": "Kung Fu Panda 4",
    "id": 16748,
    "alt_title": "Ímyndaðir vinir á toppnum",
    "release_year": 2024,
    "poster_url": "https://kvikmyndir.is/images/poster/16748_500.jpg",
    "rating_urls": [
      "http://imdb.com/title/tt21692408",
      "http://imdb.com/title/tt21692408"
    ],
    "content_rating": "Öllum leyfð",
    "description": "Po er um það bil að verða andlegur leiðtogi í Friðardanum, en þá þarf einhver að taka við stöðu hans sem Drekastríðsmaður. Po þarf nú að þjálfa nýja kung fu iðkendur í starfið og mæta nýjum þorpara sem kallast Kameljónið en í honum búa allir óþokkar fortíðar.",
    "genres": [
      "Spenna",
      "Ævintýri",
      "Teiknað"
    ],
    "duration_in_mins": 94,
    "language": [
      "Enska"
    ],
    "trailer_url": "https://www.youtube.com/watch?v=_inKs4eeHiI",
    "cinema_showtimes": {
      "Sambíóin Álfabakka": [
        {
          "time": "2024-06-01T13:00:00.000Z",
          "purchase_url": "https://kvikmyndir.is/kvikmyndir/showtime_redirect.php?id=1592148b-7f32-4c7e-8e69-9d15616b6e0b",
          "hall": "Salur 2"
        },
        {
          "time": "2024-06-01T15:00:00.000Z",
          "purchase_url": "https://kvikmyndir.is/kvikmyndir/showtime_redirect.php?id=7a84890b-9612-43f4-a566-0f1b105689b6",
          "hall": "Salur 2"
        }
      ]
    }
  },
  {
    "title": "Love Lies Bleeding",
    "id": 16724,
    "alt_title": "Leikstjórn",
    "release_year": 2024,
    "poster_url": "https://kvikmyndir.is/images/poster/16724_500.jpg",
    "rating_urls": [
      "http://imdb.com/title/tt19637052",
      "http://imdb.com/title/tt19637052"
    ],
    "content_rating": "Bönnuð innan 16 ára",
    "description": "Líkamsræktareigandinn Lou verður ástfanginn af Jackie, metnaðarfullri vaxtarræktarkonu sem komin er til Las Vegas til að láta drauma sína rætast. En ást þeirra hefur ofbeldi í för með sér, og dregur þau djúpt niður í glæpavef fjölskyldu Lou.",
    "genres": [
      "Spenna",
      "Glæpa",
      "Ævintýri"
    ],
    "duration_in_mins": 104,
    "language": [
      "Enska"
    ],
    "trailer_url": "https://www.youtube.com/watch?v=BF_J3-DmiS0",
    "cinema_showtimes": {
      "Bíó Paradís": [
        {
          "time": "2024-06-01T21:10:00.000Z",
          "purchase_url": "https://kvikmyndir.is/kvikmyndir/showtime_redirect.php?id=8b20ac67-a23d-41be-b707-9ea82db15327",
          "hall": "Salur 3"
        }
      ]
    }
  },
  {
    "title": "Showing Up",
    "id": 16789,
    "alt_title": "Nýja Pamela Anderson - Fyrsta mynd!",
    "release_year": 2022,
    "poster_url": "https://kvikmyndir.is/images/poster/16789_500.jpg",
    "rating_urls": [
      "http://imdb.com/title/tt13923216",
      "http://imdb.com/title/tt13923216"
    ],
    "content_rating": "Bönnuð innan 12 ára",
    "description": "Dramatísk gamanmynd um skúlptúrlistamann sem undirbýr sýningu sem gæti breytt ferlinum til frambúðar. Í aðdragandanum skoðar hún samband sitt við fjölskyldu, vini og samstarfsmenn.",
    "genres": [
      "Gaman",
      "Drama"
    ],
    "duration_in_mins": 107,
    "language": [
      "Enska"
    ],
    "trailer_url": "https://www.youtube.com/watch?v=wELPTxJ2YZY",
    "cinema_showtimes": {
      "Bíó Paradís": [
        {
          "time": "2024-06-01T19:00:00.000Z",
          "purchase_url": "https://kvikmyndir.is/kvikmyndir/showtime_redirect.php?id=8725a673-3af7-4526-8bf4-fd5dc33efd7e",
          "hall": "Salur 3"
        }
      ]
    }
  },
  {
    "title": "Challengers",
    "id": 16079,
    "alt_title": "The Fall Guy flaug á toppinn",
    "release_year": 2023,
    "poster_url": "https://kvikmyndir.is/images/poster/1736149_500-1704376990.jpg",
    "rating_urls": [
      "http://imdb.com/title/tt16426418",
      "http://imdb.com/title/tt16426418"
    ],
    "content_rating": "Bönnuð innan 12 ára",
    "description": "Tennisleikarinn Tashi, sem nú hefur snúið sér að þjálfun, er búin að gera eiginmann sinn, Art, að heimsþekktum sigurvegara á mörgum risamótum. Eftir mörg töp í röð ákveður hún, til að koma Art aftur á sigurbraut, að skrá hann á áskorendamót þar sem mótspilarar eru mun viðráðanlegri. Þar mætir hann fyrrum besta vini sínum og fyrrverandi kærasta Tashi.",
    "genres": [
      "Rómantík",
      "Drama",
      "Íþróttir"
    ],
    "duration_in_mins": 131,
    "language": [
      "Enska"
    ],
    "trailer_url": "https://www.youtube.com/watch?v=MDnVk5jIJr0",
    "cinema_showtimes": {
      "Sambíóin Álfabakka": [
        {
          "time": "2024-06-01T21:20:00.000Z",
          "purchase_url": "https://kvikmyndir.is/kvikmyndir/showtime_redirect.php?id=103c2285-76ac-494c-810c-851ed9c46988",
          "hall": "Salur 2"
        }
      ]
    }
  },
  {
    "title": "Immaculate",
    "id": 16828,
    "alt_title": "Apar taka sér stöðu á toppinum",
    "release_year": 2024,
    "poster_url": "https://kvikmyndir.is/images/poster/16828_500.jpg",
    "rating_urls": [
      "http://imdb.com/title/tt23137390",
      "http://imdb.com/title/tt23137390"
    ],
    "content_rating": "Bönnuð innan 16 ára",
    "description": "Bandaríska nunnan Cecilia fer í klaustur langt uppi í sveit á Ítalíu, á fallegum stað. Hún fær blíðar móttökur en það breytist fljótt í hræðilega martröð enda reynist nýja heimilið búa yfir myrkum leyndarmálum og ólýsanlegum hryllingi.",
    "genres": [
      "Hrollvekja"
    ],
    "duration_in_mins": 89,
    "language": [
      "Ítalska"
    ],
    "trailer_url": "https://www.youtube.com/watch?v=ewxS9Z-XXYo",
    "cinema_showtimes": {
      "Bíó Paradís": [
        {
          "time": "2024-06-01T21:40:00.000Z",
          "purchase_url": "https://kvikmyndir.is/kvikmyndir/showtime_redirect.php?id=03c41644-a484-426a-931f-0f3cb03683cc",
          "hall": "Salur 2"
        }
      ]
    }
  },
  {
    "title": "Kuldi",
    "id": 16170,
    "alt_title": "Cold",
    "release_year": 2023,
    "poster_url": "https://kvikmyndir.is/images/poster/kuldi_poster_-1691405627.jpg",
    "rating_urls": [
      "http://imdb.com/title/tt21976444",
      "http://imdb.com/title/tt21976444"
    ],
    "content_rating": "Bönnuð innan 14 ára",
    "description": "Þegar Óðinn byrjar að rannsaka áratuga gömul dauðsföll á unglingaheimili, fer hann að gruna að óhugnalegir atburðir þaðan tengist dularfullu sjálfsmorði eiginkonu hans — sem og skringilegri hegðun táningsdóttur hans.",
    "genres": [
      "Drama",
      "Spennutryllir",
      "Glæpa",
      "Íslensk mynd"
    ],
    "duration_in_mins": 96,
    "language": [
      "Íslenska"
    ],
    "trailer_url": "https://www.youtube.com/watch?v=9v0b3felm5Q",
    "cinema_showtimes": {
      "Bíó Paradís": [
        {
          "time": "2024-06-01T19:40:00.000Z",
          "purchase_url": "https://kvikmyndir.is/kvikmyndir/showtime_redirect.php?id=c78333d8-0af9-4ba5-8d0c-801ba995ebbc",
          "hall": "Salur 2"
        }
      ]
    }
  }
]